docs/source/conf.py
tests/__init__.py
tests/test_data_generator.py
tests/test_data_generator_advanced.py
tests/test_data_processor.py
tests/test_stats_model_arima.py
tests/test_stats_model_garch.py
timeseries_compute/__init__.py
timeseries_compute/data_generator.py
timeseries_compute/data_processor.py
timeseries_compute/export_util.py
timeseries_compute/spillover_processor.py
timeseries_compute/stats_model.py
timeseries_compute/examples/__init__.py
timeseries_compute/examples/example_multivariate_garch.py
timeseries_compute/examples/example_univariate_garch.py
timeseries_compute-0.8.0.dist-info/licenses/LICENSE
timeseries_compute-0.8.0.dist-info/METADATA
timeseries_compute-0.8.0.dist-info/WHEEL
timeseries_compute-0.8.0.dist-info/top_level.txt
timeseries_compute-0.8.0.dist-info/RECORD
