Metadata-Version: 2.4
Name: timeseries_compute
Version: 0.8.0
Summary: A package for time series data processing and modeling using ARIMA and GARCH models
Author-email: Garth Mortensen <mortensengarth@hotmail.com>
License: MIT
Project-URL: Homepage, https://github.com/garthmortensen/timeseries-compute
Classifier: Programming Language :: Python :: 3
Classifier: Programming Language :: Python :: 3.11
Classifier: Programming Language :: Python :: 3.12
Classifier: Programming Language :: Python :: 3.13
Classifier: Operating System :: OS Independent
Classifier: Development Status :: 2 - Pre-Alpha
Classifier: Framework :: Pydantic :: 2
Classifier: Framework :: Pytest
Classifier: Framework :: Sphinx
Classifier: Natural Language :: English
Requires-Python: >=3.11
License-File: LICENSE
Requires-Dist: arch==7.2.0
Requires-Dist: certifi==2025.1.31
Requires-Dist: cffi==1.17.1
Requires-Dist: charset-normalizer==3.4.1
Requires-Dist: cryptography==44.0.2
Requires-Dist: idna==3.10
Requires-Dist: numpy==2.2.3
Requires-Dist: packaging==24.2
Requires-Dist: pandas==2.2.3
Requires-Dist: patsy==1.0.1
Requires-Dist: pycparser==2.22
Requires-Dist: python-dateutil==2.9.0.post0
Requires-Dist: pytz==2025.1
Requires-Dist: requests==2.32.3
Requires-Dist: scipy==1.15.2
Requires-Dist: six==1.17.0
Requires-Dist: statsmodels==0.14.4
Requires-Dist: tabulate==0.9.0
Requires-Dist: tzdata==2025.1
Requires-Dist: urllib3==2.3.0
Provides-Extra: dev
Requires-Dist: black==25.1.0; extra == "dev"
Requires-Dist: build==1.2.2.post1; extra == "dev"
Requires-Dist: click==8.1.8; extra == "dev"
Requires-Dist: coverage==7.6.12; extra == "dev"
Requires-Dist: flake8==7.2.0; extra == "dev"
Requires-Dist: iniconfig==2.0.0; extra == "dev"
Requires-Dist: mypy-extensions==1.0.0; extra == "dev"
Requires-Dist: pathspec==0.12.1; extra == "dev"
Requires-Dist: platformdirs==4.3.6; extra == "dev"
Requires-Dist: pluggy==1.5.0; extra == "dev"
Requires-Dist: pyproject_hooks==1.2.0; extra == "dev"
Requires-Dist: pytest==8.3.5; extra == "dev"
Requires-Dist: pytest-cov==6.0.0; extra == "dev"
Requires-Dist: twine==6.1.0; extra == "dev"
Requires-Dist: commitizen; extra == "dev"
Provides-Extra: docs
Requires-Dist: alabaster==1.0.0; extra == "docs"
Requires-Dist: babel==2.17.0; extra == "docs"
Requires-Dist: docutils==0.21.2; extra == "docs"
Requires-Dist: imagesize==1.4.1; extra == "docs"
Requires-Dist: jaraco.classes==3.4.0; extra == "docs"
Requires-Dist: jaraco.context==6.0.1; extra == "docs"
Requires-Dist: jaraco.functools==4.1.0; extra == "docs"
Requires-Dist: jeepney==0.9.0; extra == "docs"
Requires-Dist: Jinja2==3.1.5; extra == "docs"
Requires-Dist: keyring==25.6.0; extra == "docs"
Requires-Dist: markdown-it-py==3.0.0; extra == "docs"
Requires-Dist: MarkupSafe==3.0.2; extra == "docs"
Requires-Dist: mdurl==0.1.2; extra == "docs"
Requires-Dist: more-itertools==10.6.0; extra == "docs"
Requires-Dist: nh3==0.2.21; extra == "docs"
Requires-Dist: Pygments==2.19.1; extra == "docs"
Requires-Dist: readme_renderer==44.0; extra == "docs"
Requires-Dist: requests-toolbelt==1.0.0; extra == "docs"
Requires-Dist: rfc3986==2.0.0; extra == "docs"
Requires-Dist: rich==13.9.4; extra == "docs"
Requires-Dist: SecretStorage==3.3.3; extra == "docs"
Requires-Dist: snowballstemmer==2.2.0; extra == "docs"
Requires-Dist: Sphinx==8.2.3; extra == "docs"
Requires-Dist: sphinx-rtd-theme==3.0.2; extra == "docs"
Requires-Dist: sphinxcontrib-applehelp==2.0.0; extra == "docs"
Requires-Dist: sphinxcontrib-devhelp==2.0.0; extra == "docs"
Requires-Dist: sphinxcontrib-htmlhelp==2.1.0; extra == "docs"
Requires-Dist: sphinxcontrib-jquery==4.1; extra == "docs"
Requires-Dist: sphinxcontrib-jsmath==1.0.1; extra == "docs"
Requires-Dist: sphinxcontrib-qthelp==2.0.0; extra == "docs"
Requires-Dist: sphinxcontrib-serializinghtml==2.0.0; extra == "docs"
Dynamic: license-file
